covideo/__init__.py
covideo-0.0.4.dist-info/LICENSE
covideo-0.0.4.dist-info/METADATA
covideo-0.0.4.dist-info/WHEEL
covideo-0.0.4.dist-info/entry_points.txt
covideo-0.0.4.dist-info/top_level.txt
covideo-0.0.4.dist-info/RECORD
