Metadata-Version: 2.1
Name: covideo
Version: 0.0.4
Summary: Easily clip and merge MP4 videos
Home-page: https://github.com/yikeke/covideo
Author: yikeke
Author-email: yikeke@pingcap.com
License: UNKNOWN
Keywords: video-clipping
Platform: UNKNOWN
